contaxy/__init__.py
contaxy/_about.py
contaxy/_cli.py
contaxy/config.py
contaxy/main.py
contaxy/api/__init__.py
contaxy/api/api.py
contaxy/api/dependencies.py
contaxy/api/error_handling.py
contaxy/api/endpoints/__init__.py
contaxy/api/endpoints/auth.py
contaxy/api/endpoints/deployment.py
contaxy/api/endpoints/extension.py
contaxy/api/endpoints/file.py
contaxy/api/endpoints/json_db.py
contaxy/api/endpoints/project.py
contaxy/api/endpoints/seed.py
contaxy/api/endpoints/system.py
contaxy/api/endpoints/user.py
contaxy/api/endpoints/templates/register-admin-success.html.j2
contaxy/api/endpoints/templates/register-admin.html.j2
contaxy/clients/__init__.py
contaxy/clients/auth.py
contaxy/clients/components.py
contaxy/clients/deployment.py
contaxy/clients/extension.py
contaxy/clients/file.py
contaxy/clients/json_db.py
contaxy/clients/project.py
contaxy/clients/shared.py
contaxy/clients/system.py
contaxy/managers/__init__.py
contaxy/managers/auth.py
contaxy/managers/components.py
contaxy/managers/extension.py
contaxy/managers/project.py
contaxy/managers/seed.py
contaxy/managers/system.py
contaxy/managers/deployment/__init__.py
contaxy/managers/deployment/docker.py
contaxy/managers/deployment/docker_utils.py
contaxy/managers/deployment/kube_utils.py
contaxy/managers/deployment/kubernetes.py
contaxy/managers/deployment/manager.py
contaxy/managers/deployment/utils.py
contaxy/managers/file/__init__.py
contaxy/managers/file/azure_blob.py
contaxy/managers/file/minio.py
contaxy/managers/json_db/__init__.py
contaxy/managers/json_db/inmemory_dict.py
contaxy/managers/json_db/postgres.py
contaxy/operations/__init__.py
contaxy/operations/auth.py
contaxy/operations/components.py
contaxy/operations/deployment.py
contaxy/operations/extension.py
contaxy/operations/file.py
contaxy/operations/json_db.py
contaxy/operations/project.py
contaxy/operations/seed.py
contaxy/operations/system.py
contaxy/schema/__init__.py
contaxy/schema/auth.py
contaxy/schema/deployment.py
contaxy-0.0.23.dist-info/LICENSE
contaxy-0.0.23.dist-info/METADATA
contaxy-0.0.23.dist-info/WHEEL
contaxy-0.0.23.dist-info/entry_points.txt
contaxy-0.0.23.dist-info/top_level.txt
contaxy-0.0.23.dist-info/RECORD
