Metadata-Version: 2.1
Name: contaxy
Version: 0.0.23
Summary: Python package template.
Home-page: https://github.com/ml-tooling/contaxy
Author: ML Tooling Team
Author-email: team@mltooling.org
License: MIT
Project-URL: Changelog, https://github.com/ml-tooling/contaxy/releases
Project-URL: Issue Tracker, https://github.com/ml-tooling/contaxy/issues
Project-URL: Documentation, https://github.com/ml-tooling/contaxy#documentation
Project-URL: Source, https://github.com/ml-tooling/contaxy
Platform: UNKNOWN
Classifier: Development Status :: 4 - Beta
Classifier: Intended Audience :: Developers
Classifier: Intended Audience :: Science/Research
Classifier: Intended Audience :: Information Technology
Classifier: License :: OSI Approved :: MIT License
Classifier: Natural Language :: English
Classifier: Operating System :: OS Independent
Classifier: Programming Language :: Python :: 3 :: Only
Classifier: Programming Language :: Python :: 3
Classifier: Programming Language :: Python :: 3.6
Classifier: Programming Language :: Python :: 3.7
Classifier: Programming Language :: Python :: 3.8
Classifier: Programming Language :: Python :: 3.9
Classifier: Programming Language :: Python :: Implementation :: PyPy
Classifier: Programming Language :: Python :: Implementation :: CPython
Classifier: Topic :: Software Development
Classifier: Topic :: Software Development :: Libraries
Classifier: Topic :: Software Development :: Libraries :: Python Modules
Classifier: Topic :: Scientific/Engineering :: Artificial Intelligence
Classifier: Topic :: Scientific/Engineering
Classifier: Topic :: Utilities
Requires-Python: >=3.8
License-File: LICENSE
Requires-Dist: typer
Requires-Dist: pydantic[dotenv,email]
Requires-Dist: fastapi (==0.75.2)
Requires-Dist: requests
Requires-Dist: loguru
Requires-Dist: filetype
Requires-Dist: addict
Requires-Dist: requests-toolbelt
Requires-Dist: shortuuid
Requires-Dist: slugify
Provides-Extra: dev
Requires-Dist: setuptools ; extra == 'dev'
Requires-Dist: wheel ; extra == 'dev'
Requires-Dist: twine ; extra == 'dev'
Requires-Dist: flake8 ; extra == 'dev'
Requires-Dist: pytest ; extra == 'dev'
Requires-Dist: pytest-mock ; extra == 'dev'
Requires-Dist: pytest-cov ; extra == 'dev'
Requires-Dist: mypy ; extra == 'dev'
Requires-Dist: types-python-slugify ; extra == 'dev'
Requires-Dist: types-requests ; extra == 'dev'
Requires-Dist: types-cachetools ; extra == 'dev'
Requires-Dist: black ; extra == 'dev'
Requires-Dist: pydocstyle ; extra == 'dev'
Requires-Dist: isort ; extra == 'dev'
Requires-Dist: lazydocs ; extra == 'dev'
Requires-Dist: locust ; extra == 'dev'
Requires-Dist: pyinstrument ; extra == 'dev'
Requires-Dist: pytest-profiling ; extra == 'dev'
Requires-Dist: devtools[pygments] ; extra == 'dev'
Requires-Dist: ipykernel ; extra == 'dev'
Requires-Dist: universal-build ; extra == 'dev'
Requires-Dist: requests ; extra == 'dev'
Provides-Extra: server
Requires-Dist: kubernetes ; extra == 'server'
Requires-Dist: docker ; extra == 'server'
Requires-Dist: fastapi-utils ; extra == 'server'
Requires-Dist: python-multipart ; extra == 'server'
Requires-Dist: streaming-form-data ; extra == 'server'
Requires-Dist: psutil ; extra == 'server'
Requires-Dist: uvicorn ; extra == 'server'
Requires-Dist: sqlalchemy (>=1.4.0) ; extra == 'server'
Requires-Dist: psycopg2 ; extra == 'server'
Requires-Dist: shortuuid ; extra == 'server'
Requires-Dist: python-slugify ; extra == 'server'
Requires-Dist: minio ; extra == 'server'
Requires-Dist: azure-storage-blob ; extra == 'server'
Requires-Dist: python-jose[cryptography] ; extra == 'server'
Requires-Dist: passlib[bcrypt] ; extra == 'server'
Requires-Dist: json-merge-patch ; extra == 'server'
Requires-Dist: jsonpath-ng ; extra == 'server'
Requires-Dist: jinja2 ; extra == 'server'
Requires-Dist: requests-oauthlib ; extra == 'server'
Requires-Dist: faker ; extra == 'server'
